Metadata-Version: 2.1
Name: cube-recognizer-for-agv
Version: 1.0.1
Summary: Cube recognition
Author: Anonymous
Author-email: anonymous@tsstudio.top
License: GNU General Public License v3.0
License-File: LICENSE
